artefactscomparison/__init__.py
artefactscomparison/__main__.py
artefactscomparison/cli.py
artefactscomparison/compare.py
artefactscomparison/csv_parser.py
artefactscomparison/report.py
tests/__init__.py
tests/test_compare.py
tests/test_csv_parser.py
tests/test_report.py
artefactscomparison-0.2.0.dist-info/LICENSE
artefactscomparison-0.2.0.dist-info/METADATA
artefactscomparison-0.2.0.dist-info/WHEEL
artefactscomparison-0.2.0.dist-info/entry_points.txt
artefactscomparison-0.2.0.dist-info/top_level.txt
artefactscomparison-0.2.0.dist-info/RECORD
