Metadata-Version: 2.1
Name: artefactscomparison
Version: 0.2.0
Summary: Compare and report on two artefacts summaries.
Home-page: https://github.com/EBoisseauSierra/artefacts_comparison
Author: Étienne Boisseau-Sierra
Author-email: etienne.boisseau.sierra@gmail.com
Maintainer: Étienne Boisseau-Sierra
Maintainer-email: etienne.boisseau.sierra@gmail.com
License: MIT
Classifier: License :: OSI Approved :: MIT License
Classifier: Operating System :: OS Independent
Classifier: Programming Language :: Python :: 3
Classifier: Programming Language :: Python :: 3.9
Requires-Python: >=3.9
License-File: LICENSE
Requires-Dist: click (>=7.0)
Provides-Extra: dev
Requires-Dist: build ; extra == 'dev'
Requires-Dist: black ; extra == 'dev'
Requires-Dist: flake8 ; extra == 'dev'
Requires-Dist: pre-commit ; extra == 'dev'
Requires-Dist: pylint ; extra == 'dev'
Requires-Dist: twine ; extra == 'dev'
Provides-Extra: test
Requires-Dist: pytest ; extra == 'test'
Requires-Dist: pytest-cov ; extra == 'test'
